Metadata-Version: 2.1
Name: sick-dict
Version: 0.1
Summary: SickDict - An IDE-friendly python dictionary
Home-page: https://github.com/singhgautam7/Python-GoldMine/tree/master/sick_dict
Author: Gautam Rajeev Singh
Author-email: gautamsingh1997@gmail.com
License: MIT
Keywords: pyton dictionary dict json
Platform: UNKNOWN
Classifier: Programming Language :: Python :: 3
Classifier: License :: OSI Approved :: MIT License
Classifier: Operating System :: OS Independent
Requires-Python: >=3.0
License-File: LICENSE.txt
